{
  "title": "Assessment Events Test",
  "levels": [
    {
      "id": 153,
      "title": "Prerequisite Assessment",
      "max_score": 0,
      "level_type": "ASSESSMENT_LEVEL",
      "estimated_duration": 3,
      "order": 1,
      "questions": "[{\"answer_required\":false,\"order\":0,\"penalty\":0,\"points\":0,\"text\":\"Gender\",\"question_type\":\"MCQ\",\"choices\":[{\"text\":\"Male\",\"order\":0,\"is_correct\":false},{\"text\":\"Female\",\"order\":1,\"is_correct\":false},{\"text\":\"Other\",\"order\":2,\"is_correct\":false},{\"text\":\"Prefer not to answer\",\"order\":3,\"is_correct\":false}]},{\"answer_required\":false,\"order\":1,\"penalty\":0,\"points\":0,\"text\":\"What is your age? Insert number.\",\"question_type\":\"FFQ\",\"correct_choices\":[]},{\"answer_required\":false,\"order\":2,\"penalty\":0,\"points\":0,\"text\":\"Skills and knowledge - evaluate yourself.\",\"question_type\":\"EMI\",\"rows\":[\"Knowledge of GNU/Linux OS as a user\",\"Knowledge of GNU/Linux OS as an administrator\",\"Kali Linux\",\"ssh/scp tools\"],\"cols\":[\"Low\",\"Average\",\"Deep\"],\"correct_answers\":[{\"x\":-1,\"y\":-1}]}]",
      "assessment_type": "QUESTIONNAIRE"
    },
    {
      "id": 195,
      "title": "Test!",
      "max_score": 0,
      "level_type": "ASSESSMENT_LEVEL",
      "estimated_duration": 7,
      "order": 6,
      "questions": "[{\"answer_required\":true,\"order\":0,\"penalty\":10,\"points\":20,\"text\":\"What is 5 + 5\",\"question_type\":\"FFQ\",\"correct_choices\":[\"10\",\"ten\"]},{\"answer_required\":true,\"order\":1,\"penalty\":5,\"points\":20,\"text\":\"Which of these statements are true\",\"question_type\":\"MCQ\",\"choices\":[{\"text\":\"Sky is blue\",\"order\":0,\"is_correct\":true},{\"text\":\"Angular is backend framework\",\"order\":1,\"is_correct\":false},{\"text\":\"Cat is an animal\",\"order\":2,\"is_correct\":true},{\"text\":\"Pizza is healthy\",\"order\":3,\"is_correct\":false},{\"text\":\"Pizza is tasty\",\"order\":4,\"is_correct\":true}]},{\"answer_required\":true,\"order\":2,\"penalty\":5,\"points\":30,\"text\":\"Match following items\",\"question_type\":\"EMI\",\"rows\":[\"Cat\",\"Dog\",\"Apple tree\",\"Cow\",\"Grass\",\"Snake\",\"Bird\"],\"cols\":[\"Animal\",\"Flower\"],\"correct_answers\":[{\"x\":0,\"y\":0},{\"x\":1,\"y\":0},{\"x\":2,\"y\":1},{\"x\":3,\"y\":0},{\"x\":4,\"y\":1},{\"x\":5,\"y\":0},{\"x\":6,\"y\":0}]}]",
      "assessment_type": "TEST"
    },
    {
      "id": 158,
      "title": "Happy hacking!",
      "max_score": 0,
      "level_type": "ASSESSMENT_LEVEL",
      "estimated_duration": 4,
      "order": 7,
      "questions": "[{\"answer_required\":false,\"order\":0,\"penalty\":0,\"points\":0,\"text\":\"What was the hardest task for me?\",\"question_type\":\"FFQ\",\"correct_choices\":[]},{\"answer_required\":false,\"order\":1,\"penalty\":0,\"points\":0,\"text\":\"How do you rate this training?\",\"question_type\":\"EMI\",\"rows\":[\"Challenging\",\"Interesting\",\"Funny\",\"Understandable\"],\"cols\":[\"1 (not at all)\",\"2\",\"3 (yes, indeed)\"],\"correct_answers\":[{\"x\":-1,\"y\":-1}]}]",
      "assessment_type": "QUESTIONNAIRE"
    }
  ],
  "estimated_duration": 14
}
